symrank-0.1.5.dist-info/METADATA
symrank-0.1.5.dist-info/WHEEL
symrank-0.1.5.dist-info/licenses/LICENSE
symrank-0.1.5.dist-info/licenses/NOTICE
symrank/__init__.py
symrank/cosine_similarity.py
symrank/cosine_similarity_batch.py
symrank/cosine_similarity_simd.py
symrank/py.typed
symrank/symrank.cpython-311-darwin.so
symrank-0.1.5.dist-info/RECORD
