Metadata-Version: 2.4
Name: symrank
Version: 0.1.5
Classifier: Development Status :: 4 - Beta
Classifier: License :: OSI Approved :: Apache Software License
Classifier: Programming Language :: Python :: 3
Classifier: Programming Language :: Python :: 3 :: Only
Classifier: Programming Language :: Python :: 3.10
Classifier: Programming Language :: Python :: 3.11
Classifier: Programming Language :: Python :: 3.12
Classifier: Programming Language :: Python :: 3.13
Classifier: Programming Language :: Rust
Classifier: Programming Language :: Python :: Implementation :: CPython
Classifier: Intended Audience :: Developers
Classifier: Topic :: Scientific/Engineering
Requires-Dist: maturin>=1.8.3 ; extra == 'dev'
Requires-Dist: pytest>=8.3.5 ; extra == 'dev'
Requires-Dist: ruff>=0.11.10 ; extra == 'dev'
Requires-Dist: mypy>=1.15.0 ; extra == 'dev'
Requires-Dist: scikit-learn>=1.6.1 ; extra == 'benchmarks'
Requires-Dist: numpy>=2.2.5 ; extra == 'benchmarks'
Requires-Dist: datasets>=3.6.0 ; extra == 'benchmarks'
Provides-Extra: dev
Provides-Extra: benchmarks
License-File: LICENSE
License-File: NOTICE
Summary: High-performance cosine similarity ranking for Retrieval-Augmented Generation (RAG) pipelines, vector search, and information retrieval, with a Python interface powered by a Rust backend.
Keywords: symrank,vector similarity,cosine similarity,ranking,reranking,retrieval,rag,retrieval-augmented-generation,semantic search,embedding search,vector search,machine learning,information retrieval
Author-email: Ross Armstrong <ross.armstrong@analyticsinmotion.com>
Requires-Python: >=3.10
Project-URL: Repository, https://github.com/analyticsinmotion/symrank
Project-URL: Bug Tracker, https://github.com/analyticsinmotion/symrank/issues
